{
  "id": 13,
  "title": "Family Relationships",
  "titleHindi": "पारिवारिक संबंध",
  "level": "beginner",
  "category": "Family",
  "description": "Learn Hindi vocabulary for family members and understand the complex family relationship terms in Indian culture.",
  "descriptionHindi": "परिवार के सदस्यों के लिए हिंदी शब्दावली सीखें और भारतीय संस्कृति में जटिल पारिवारिक संबंध शब्दों को समझें।",
  "estimatedTimeMinutes": 30,
  "sections": [
    {
      "id": 1,
      "title": "Introduction",
      "titleHindi": "परिचय",
      "content": "Family plays a central role in Indian culture, and Hindi has specific terms for various family relationships that might not have direct equivalents in English. In this lesson, you'll learn the Hindi words for immediate family members as well as extended family relations. The terms often vary based on whether the relation is from the maternal or paternal side, making the system quite elaborate but precise.",
      "contentHindi": "भारतीय संस्कृति में परिवार एक केंद्रीय भूमिका निभाता है, और हिंदी में विभिन्न पारिवारिक संबंधों के लिए विशिष्ट शब्द हैं जिनके अंग्रेजी में सीधे समकक्ष नहीं हो सकते हैं। इस पाठ में, आप निकट परिवार के सदस्यों के साथ-साथ विस्तारित परिवार संबंधों के लिए हिंदी शब्द सीखेंगे। शब्द अक्सर इस बात पर भिन्न होते हैं कि संबंध मातृ या पितृ पक्ष से है, जिससे प्रणाली काफी विस्तृत लेकिन सटीक हो जाती है।"
    },
    {
      "id": 2,
      "title": "Immediate Family",
      "titleHindi": "निकट परिवार",
      "content": "Let's begin with the terms for immediate family members:\n\n1. Father: 'Pita' (पिता) or 'Papa' (पापा) - Pronunciation: pi-taa or paa-paa\n2. Mother: 'Mata' (माता) or 'Maa' (माँ) - Pronunciation: maa-taa or maa\n3. Brother: 'Bhai' (भाई) - Pronunciation: bhaa-ee\n4. Sister: 'Bahen' (बहन) - Pronunciation: buh-hen\n5. Son: 'Beta' (बेटा) - Pronunciation: bay-taa\n6. Daughter: 'Beti' (बेटी) - Pronunciation: bay-tee\n7. Husband: 'Pati' (पति) - Pronunciation: puh-tee\n8. Wife: 'Patni' (पत्नी) - Pronunciation: put-nee\n9. Child: 'Bachcha' (बच्चा) - Pronunciation: buch-chaa\n10. Parents: 'Mata-Pita' (माता-पिता) - Pronunciation: maa-taa-pi-taa",
      "contentHindi": "आइए निकट परिवार के सदस्यों के लिए शब्दों से शुरू करें:\n\n1. पिता या पापा (Father) - उच्चारण: पि-ता या पा-पा\n2. माता या माँ (Mother) - उच्चारण: मा-ता या माँ\n3. भाई (Brother) - उच्चारण: भा-ई\n4. बहन (Sister) - उच्चारण: ब-हन\n5. बेटा (Son) - उच्चारण: बे-टा\n6. बेटी (Daughter) - उच्चारण: बे-टी\n7. पति (Husband) - उच्चारण: प-ति\n8. पत्नी (Wife) - उच्चारण: पत्-नी\n9. बच्चा (Child) - उच्चारण: बच्-चा\n10. माता-पिता (Parents) - उच्चारण: मा-ता-पि-ता"
    },
    {
      "id": 3,
      "title": "Grandparents and Grandchildren",
      "titleHindi": "दादा-दादी/नाना-नानी और पोते-पोतियाँ/नाती-नातिन",
      "content": "Hindi makes distinctions between maternal and paternal grandparents:\n\n1. Paternal grandfather: 'Dada' (दादा) - Pronunciation: daa-daa\n2. Paternal grandmother: 'Dadi' (दादी) - Pronunciation: daa-dee\n3. Maternal grandfather: 'Nana' (नाना) - Pronunciation: naa-naa\n4. Maternal grandmother: 'Nani' (नानी) - Pronunciation: naa-nee\n\nSimilarly, terms for grandchildren vary:\n\n5. Son's son (grandson): 'Pota' (पोता) - Pronunciation: po-taa\n6. Son's daughter (granddaughter): 'Poti' (पोती) - Pronunciation: po-tee\n7. Daughter's son (grandson): 'Nati' (नाती) - Pronunciation: naa-tee\n8. Daughter's daughter (granddaughter): 'Natin' (नातिन) - Pronunciation: naa-tin",
      "contentHindi": "हिंदी में मातृ और पितृ दादा-दादी/नाना-नानी के बीच अंतर किया जाता है:\n\n1. दादा (Paternal grandfather) - उच्चारण: दा-दा\n2. दादी (Paternal grandmother) - उच्चारण: दा-दी\n3. नाना (Maternal grandfather) - उच्चारण: ना-ना\n4. नानी (Maternal grandmother) - उच्चारण: ना-नी\n\nइसी तरह, पोते-पोतियों/नाती-नातिन के लिए शब्द भिन्न होते हैं:\n\n5. पोता (Son's son/grandson) - उच्चारण: पो-ता\n6. पोती (Son's daughter/granddaughter) - उच्चारण: पो-ती\n7. नाती (Daughter's son/grandson) - उच्चारण: ना-ती\n8. नातिन (Daughter's daughter/granddaughter) - उच्चारण: ना-तिन"
    },
    {
      "id": 4,
      "title": "Uncles and Aunts",
      "titleHindi": "चाचा-ताऊ-मामा और चाची-ताई-मामी-मौसी",
      "content": "Hindi has specific terms for different types of uncles and aunts:\n\nPaternal side (father's side):\n1. Father's brother (younger): 'Chacha' (चाचा) - Pronunciation: chaa-chaa\n2. Father's brother (elder): 'Tau' (ताऊ) or 'Taya' (ताया) - Pronunciation: taa-oo or taa-yaa\n3. Father's brother's wife (younger): 'Chachi' (चाची) - Pronunciation: chaa-chee\n4. Father's brother's wife (elder): 'Tai' (ताई) - Pronunciation: taa-ee\n5. Father's sister: 'Bua' (बुआ) or 'Phuphi' (फूफी) - Pronunciation: boo-aa or foo-fee\n\nMaternal side (mother's side):\n6. Mother's brother: 'Mama' (मामा) - Pronunciation: maa-maa\n7. Mother's brother's wife: 'Mami' (मामी) - Pronunciation: maa-mee\n8. Mother's sister: 'Mausi' (मौसी) - Pronunciation: mow-see\n9. Mother's sister's husband: 'Mausa' (मौसा) - Pronunciation: mow-saa",
      "contentHindi": "हिंदी में विभिन्न प्रकार के चाचा-ताऊ-मामा और चाची-ताई-मामी-मौसी के लिए विशिष्ट शब्द हैं:\n\nपितृ पक्ष (पिता का पक्ष):\n1. चाचा (Father's younger brother) - उच्चारण: चा-चा\n2. ताऊ या ताया (Father's elder brother) - उच्चारण: ता-ऊ या ता-या\n3. चाची (Father's younger brother's wife) - उच्चारण: चा-ची\n4. ताई (Father's elder brother's wife) - उच्चारण: ता-ई\n5. बुआ या फूफी (Father's sister) - उच्चारण: बु-आ या फू-फी\n\nमातृ पक्ष (माता का पक्ष):\n6. मामा (Mother's brother) - उच्चारण: मा-मा\n7. मामी (Mother's brother's wife) - उच्चारण: मा-मी\n8. मौसी (Mother's sister) - उच्चारण: मौ-सी\n9. मौसा (Mother's sister's husband) - उच्चारण: मौ-सा"
    },
    {
      "id": 5,
      "title": "Cousins and In-laws",
      "titleHindi": "चचेरे-ममेरे-फुफेरे-मौसेरे भाई-बहन और ससुराल",
      "content": "Hindi distinguishes cousins based on the relationship:\n\n1. Father's brother's children: 'Chachera bhai/bahen' (चचेरा भाई/बहन) - Pronunciation: chuh-chay-raa bhaa-ee/buh-hen\n2. Father's sister's children: 'Phuphera bhai/bahen' (फुफेरा भाई/बहन) - Pronunciation: foo-fay-raa bhaa-ee/buh-hen\n3. Mother's brother's children: 'Mamera bhai/bahen' (ममेरा भाई/बहन) - Pronunciation: muh-may-raa bhaa-ee/buh-hen\n4. Mother's sister's children: 'Mausera bhai/bahen' (मौसेरा भाई/बहन) - Pronunciation: mow-say-raa bhaa-ee/buh-hen\n\nCommon in-law terms:\n5. Father-in-law: 'Sasur' (ससुर) - Pronunciation: suh-soor\n6. Mother-in-law: 'Saas' (सास) - Pronunciation: saas\n7. Brother-in-law (wife's brother): 'Sala' (साला) - Pronunciation: saa-laa\n8. Sister-in-law (wife's sister): 'Sali' (साली) - Pronunciation: saa-lee\n9. Brother-in-law (husband's brother): 'Devar' (देवर) - Pronunciation: day-vur\n10. Sister-in-law (husband's sister): 'Nanad' (ननद) - Pronunciation: nuh-nud",
      "contentHindi": "हिंदी में संबंध के आधार पर चचेरे-ममेरे-फुफेरे-मौसेरे भाई-बहन के बीच अंतर किया जाता है:\n\n1. चचेरा भाई/बहन (Father's brother's children) - उच्चारण: च-चे-रा भा-ई/ब-हन\n2. फुफेरा भाई/बहन (Father's sister's children) - उच्चारण: फु-फे-रा भा-ई/ब-हन\n3. ममेरा भाई/बहन (Mother's brother's children) - उच्चारण: म-मे-रा भा-ई/ब-हन\n4. मौसेरा भाई/बहन (Mother's sister's children) - उच्चारण: मौ-से-रा भा-ई/ब-हन\n\nसामान्य ससुराल शब्द:\n5. ससुर (Father-in-law) - उच्चारण: स-सुर\n6. सास (Mother-in-law) - उच्चारण: सास\n7. साला (Wife's brother) - उच्चारण: सा-ला\n8. साली (Wife's sister) - उच्चारण: सा-ली\n9. देवर (Husband's younger brother) - उच्चारण: दे-वर\n10. ननद (Husband's sister) - उच्चारण: न-नद"
    },
    {
      "id": 6,
      "title": "Common Phrases About Family",
      "titleHindi": "परिवार के बारे में सामान्य वाक्यांश",
      "content": "Here are some useful phrases to talk about your family:\n\n1. My family: 'Mera parivar' (मेरा परिवार) - Pronunciation: may-raa puh-ri-vaar\n2. I have a brother: 'Mera ek bhai hai' (मेरा एक भाई है) - Pronunciation: may-raa ek bhaa-ee hai\n3. I have two sisters: 'Meri do bahene hain' (मेरी दो बहनें हैं) - Pronunciation: may-ree do buh-hay-nain hain\n4. How many siblings do you have?: 'Aapke kitne bhai-bahen hain?' (आपके कितने भाई-बहन हैं?) - Pronunciation: aap-kay kit-nay bhaa-ee-buh-hen hain\n5. This is my mother: 'Yeh meri maa hain' (यह मेरी माँ हैं) - Pronunciation: yeh may-ree maa hain\n6. My father works at...: 'Mere pita... mein kaam karte hain' (मेरे पिता... में काम करते हैं) - Pronunciation: may-ray pi-taa... mein kaam kur-tay hain\n7. My grandparents live with us: 'Mere dada-dadi hamare saath rehte hain' (मेरे दादा-दादी हमारे साथ रहते हैं) - Pronunciation: may-ray daa-daa-daa-dee huh-maa-ray saath reh-tay hain\n8. I miss my family: 'Mujhe apne parivar ki yaad aati hai' (मुझे अपने परिवार की याद आती है) - Pronunciation: moo-jhay up-nay puh-ri-vaar kee yaad aa-tee hai\n9. We are a joint family: 'Hum ek sanyukt parivar hain' (हम एक संयुक्त परिवार हैं) - Pronunciation: hum ek sun-yukt puh-ri-vaar hain\n10. How is your family?: 'Aapka parivar kaisa hai?' (आपका परिवार कैसा है?) - Pronunciation: aap-kaa puh-ri-vaar kai-saa hai",
      "contentHindi": "यहां अपने परिवार के बारे में बात करने के लिए कुछ उपयोगी वाक्यांश हैं:\n\n1. मेरा परिवार (My family) - उच्चारण: मे-रा प-रि-वार\n2. मेरा एक भाई है (I have a brother) - उच्चारण: मे-रा एक भा-ई है\n3. मेरी दो बहनें हैं (I have two sisters) - उच्चारण: मे-री दो ब-ह-नें हैं\n4. आपके कितने भाई-बहन हैं? (How many siblings do you have?) - उच्चारण: आप-के कित-ने भा-ई-ब-हन हैं\n5. यह मेरी माँ हैं (This is my mother) - उच्चारण: यह मे-री माँ हैं\n6. मेरे पिता... में काम करते हैं (My father works at...) - उच्चारण: मे-रे पि-ता... में काम कर-ते हैं\n7. मेरे दादा-दादी हमारे साथ रहते हैं (My grandparents live with us) - उच्चारण: मे-रे दा-दा-दा-दी ह-मा-रे साथ रह-ते हैं\n8. मुझे अपने परिवार की याद आती है (I miss my family) - उच्चारण: मु-झे अप-ने प-रि-वार की याद आ-ती है\n9. हम एक संयुक्त परिवार हैं (We are a joint family) - उच्चारण: हम एक सं-युक्त प-रि-वार हैं\n10. आपका परिवार कैसा है? (How is your family?) - उच्चारण: आप-का प-रि-वार कै-सा है"
    }
  ],
  "vocabulary": [
    {
      "english": "Father",
      "hindi": "पिता/पापा",
      "pronunciation": "pi-taa/paa-paa"
    },
    {
      "english": "Mother",
      "hindi": "माता/माँ",
      "pronunciation": "maa-taa/maa"
    },
    {
      "english": "Brother",
      "hindi": "भाई",
      "pronunciation": "bhaa-ee"
    },
    {
      "english": "Sister",
      "hindi": "बहन",
      "pronunciation": "buh-hen"
    },
    {
      "english": "Son",
      "hindi": "बेटा",
      "pronunciation": "bay-taa"
    },
    {
      "english": "Daughter",
      "hindi": "बेटी",
      "pronunciation": "bay-tee"
    },
    {
      "english": "Husband",
      "hindi": "पति",
      "pronunciation": "puh-tee"
    },
    {
      "english": "Wife",
      "hindi": "पत्नी",
      "pronunciation": "put-nee"
    },
    {
      "english": "Paternal grandfather",
      "hindi": "दादा",
      "pronunciation": "daa-daa"
    },
    {
      "english": "Paternal grandmother",
      "hindi": "दादी",
      "pronunciation": "daa-dee"
    },
    {
      "english": "Maternal grandfather",
      "hindi": "नाना",
      "pronunciation": "naa-naa"
    },
    {
      "english": "Maternal grandmother",
      "hindi": "नानी",
      "pronunciation": "naa-nee"
    },
    {
      "english": "Father's brother",
      "hindi": "चाचा/ताऊ",
      "pronunciation": "chaa-chaa/taa-oo"
    },
    {
      "english": "Mother's brother",
      "hindi": "मामा",
      "pronunciation": "maa-maa"
    },
    {
      "english": "Family",
      "hindi": "परिवार",
      "pronunciation": "puh-ri-vaar"
    }
  ],
  "practiceExercises": [
    {
      "type": "multiple_choice",
      "question": "What is the Hindi word for 'Mother'?",
      "questionHindi": "हिंदी में 'Mother' क्या कहते हैं?",
      "options": ["पिता", "माता", "भाई", "बहन"],
      "correctAnswerIndex": 1
    },
    {
      "type": "multiple_choice",
      "question": "Which term refers to your father's father?",
      "questionHindi": "कौन सा शब्द आपके पिता के पिता को संदर्भित करता है?",
      "options": ["नाना", "दादा", "मामा", "चाचा"],
      "correctAnswerIndex": 1
    },
    {
      "type": "fill_blank",
      "question": "Your mother's sister is called _______ in Hindi.",
      "questionHindi": "हिंदी में आपकी माँ की बहन को _______ कहा जाता है।",
      "correctAnswer": "मौसी"
    },
    {
      "type": "true_false",
      "question": "'चाचा' (Chacha) refers to your father's younger brother in Hindi.",
      "questionHindi": "'चाचा' हिंदी में आपके पिता के छोटे भाई को संदर्भित करता है।",
      "correctAnswer": true
    },
    {
      "type": "match_pairs",
      "pairs": [
        {"left": "भाई", "right": "Brother"},
        {"left": "बहन", "right": "Sister"},
        {"left": "बेटा", "right": "Son"},
        {"left": "बेटी", "right": "Daughter"}
      ]
    }
  ],
  "culturalNotes": [
    {
      "title": "Joint Family System",
      "titleHindi": "संयुक्त परिवार प्रणाली",
      "content": "The joint family system is common in Indian culture, where multiple generations live together under one roof. This system has influenced the development of specific terms for extended family relationships. The joint family typically includes grandparents, parents, children, and sometimes uncles, aunts, and their families.",
      "contentHindi": "संयुक्त परिवार प्रणाली भारतीय संस्कृति में आम है, जहां कई पीढ़ियां एक छत के नीचे एक साथ रहती हैं। इस प्रणाली ने विस्तारित पारिवारिक संबंधों के लिए विशिष्ट शब्दों के विकास को प्रभावित किया है। संयुक्त परिवार में आमतौर पर दादा-दादी, माता-पिता, बच्चे, और कभी-कभी चाचा-चाची, मामा-मामी और उनके परिवार शामिल होते हैं।"
    },
    {
      "title": "Respect for Elders",
      "titleHindi": "बड़ों के लिए सम्मान",
      "content": "In Hindi language and culture, there's a strong emphasis on showing respect to elders. This is reflected in the language through specific pronouns and verb forms used when speaking to older family members. Children often touch the feet of elders as a sign of respect, known as 'pranaam' (प्रणाम).",
      "contentHindi": "हिंदी भाषा और संस्कृति में, बड़ों के प्रति सम्मान दिखाने पर जोर दिया जाता है। यह भाषा में उन विशिष्ट सर्वनामों और क्रिया रूपों के माध्यम से परिलक्षित होता है जिनका उपयोग बड़े परिवार के सदस्यों से बात करते समय किया जाता है। बच्चे अक्सर सम्मान के प्रतीक के रूप में बड़ों के पैर छूते हैं, जिसे 'प्रणाम' कहा जाता है।"
    }
  ],
  "relatedLessons": [1, 2, 4],
  "nextLessonId": 4
}